dansy/__init__.py
dansy/config.py
dansy/current_proteome_version.txt
dansy/dansy.py
dansy/deDANSy.py
dansy/dedansy_algorithm.py
dansy/directories.txt
dansy/enrichment_helpers.py
dansy/enrichment_plotting_helpers.py
dansy/helper.py
dansy/network_separation_helpers.py
dansy/ngramUtilities.py
dansy-0.1.0.dist-info/licenses/LICENSE
dansy-0.1.0.dist-info/METADATA
dansy-0.1.0.dist-info/WHEEL
dansy-0.1.0.dist-info/top_level.txt
dansy-0.1.0.dist-info/RECORD
