Metadata-Version: 2.4
Name: dansy
Version: 0.1.0
Summary: DANSy: Domain Architecture Network Syntax
Home-page: https://github.com/NaegleLab/DANSy
Author: Naegle Lab
Author-email: kmn4mj@virginia.edu
License: GNU General Public License v3
Project-URL: Documentation, https://naeglelab.github.io/DANSy/
Classifier: Programming Language :: Python :: 3
Classifier: Intended Audience :: Science/Research
Classifier: Operating System :: OS Independent
Requires-Python: >=3.9
License-File: LICENSE
Requires-Dist: pandas==2.2.*
Requires-Dist: numpy==2.0.*
Requires-Dist: scipy==1.13.*
Requires-Dist: networkx==3.2.*
Requires-Dist: matplotlib==3.9.*
Requires-Dist: seaborn==0.13.*
Dynamic: author
Dynamic: author-email
Dynamic: classifier
Dynamic: description
Dynamic: home-page
Dynamic: license
Dynamic: license-file
Dynamic: project-url
Dynamic: requires-dist
Dynamic: requires-python
Dynamic: summary
